PBLES/__init__.py
PBLES/event_log_dp_lstm.py
PBLES/postprocessing/__init__.py
PBLES/postprocessing/log_postprocessing.py
PBLES/preprocessing/__init__.py
PBLES/preprocessing/log_preprocessing.py
PBLES/preprocessing/log_tokenization.py
PBLES/sampling/__init__.py
PBLES/sampling/log_sampling.py
PBLES-0.0.2.dist-info/LICENSE
PBLES-0.0.2.dist-info/METADATA
PBLES-0.0.2.dist-info/WHEEL
PBLES-0.0.2.dist-info/top_level.txt
PBLES-0.0.2.dist-info/RECORD
