Metadata-Version: 2.1
Name: PBLES
Version: 0.0.2
Summary: Private Bi-LSTM Event Log Synthesizer (PBLES)
Home-page: https://github.com/martinkuhn94/PBLES.git
Author: Martin Kuhn
Author-email: martin.kuhn@dfki.de
Keywords: Event Log Synthetization,Differential Privacy,Bi-LSTM,Synthetic Data Generation
Classifier: Development Status :: 3 - Alpha
Classifier: Intended Audience :: Developers
Classifier: License :: OSI Approved :: GNU General Public License v3 (GPLv3)
Classifier: Programming Language :: Python :: 3.9
Classifier: Programming Language :: Python :: 3.10
Classifier: Programming Language :: Python :: 3.11
Requires-Python: >=3.9
License-File: LICENSE
Requires-Dist: pandas ==1.5.3
Requires-Dist: numpy ==1.23.5
Requires-Dist: tensorflow ==2.14.0
Requires-Dist: scipy ==1.12.0
Requires-Dist: keras ==2.14.0
Requires-Dist: pm4py ==2.5.2
Requires-Dist: scikit-learn ==1.4.1.post1
Requires-Dist: tensorflow-privacy ==0.9.0
Requires-Dist: openpyxl ==3.1.2
